autoland/__init__.py
autoland/__main__.py
autoland/cli.py
autoland/contents/review_correction.txt
autoland/i18n.py
autoland/locales/autoland.pot
autoland/locales/ja_JP/LC_MESSAGES/autoland.mo
autoland/locales/ja_JP/LC_MESSAGES/autoland.po
autoland/service.py
autoland-0.3.0.dist-info/METADATA
autoland-0.3.0.dist-info/WHEEL
autoland-0.3.0.dist-info/entry_points.txt
autoland-0.3.0.dist-info/licenses/LICENSE
autoland-0.3.0.dist-info/RECORD
