Metadata-Version: 2.4
Name: autoland
Version: 0.3.0
Summary: A CLI tool that automatically fixes and merges GitHub PRs using AI agents
License-Expression: MIT
License-File: LICENSE
Keywords: github,pull-request,automation,ai,cli
Author: abc inc.
Author-email: oss@abckk.dev
Requires-Python: >=3.11,<4
Classifier: Development Status :: 4 - Beta
Classifier: Intended Audience :: Developers
Classifier: Operating System :: OS Independent
Classifier: Programming Language :: Python :: 3
Classifier: Programming Language :: Python :: 3.11
Classifier: Programming Language :: Python :: 3.12
Classifier: Programming Language :: Python :: 3.13
Classifier: Topic :: Software Development
Classifier: Topic :: System :: Systems Administration
Requires-Dist: click (>=8.3.0,<9.0.0)
Project-URL: Homepage, https://github.com/abc1nc/ai-autoland
Project-URL: Repository, https://github.com/abc1nc/ai-autoland
